CHANGES.txt
LICENCE.txt
MANIFEST.in
README.md
VERSION.txt
requirements.txt
setup.py
tbx/__init__.py
tbx/bytes.py
tbx/code.py
tbx/file.py
tbx/ftp.py
tbx/log.py
tbx/network.py
tbx/process.py
tbx/sequential.py
tbx/service.py
tbx/settings.py
tbx/template.py
tbx/text.py
tbx/web.py
tbx.egg-info/PKG-INFO
tbx.egg-info/SOURCES.txt
tbx.egg-info/dependency_links.txt
tbx.egg-info/requires.txt
tbx.egg-info/top_level.txt