Metadata-Version: 1.1
Name: tbx
Version: 1.9.1
Summary: Python Toolbox Library. Collection of useful tools and snippets.
Home-page: https://github.com/ronhanson/python-tbx
Author: Ronan Delacroix
Author-email: ronan.delacroix@gmail.com
License: The MIT License (MIT)
